xThermal/H2O.py
xThermal/H2ONaCl.py
xThermal/NaCl.py
xThermal/_H2O.so
xThermal/_H2ONaCl.so
xThermal/_NaCl.so
xThermal/__init__.py
xThermal-0.1.1.dist-info/METADATA
xThermal-0.1.1.dist-info/WHEEL
xThermal-0.1.1.dist-info/top_level.txt
xThermal-0.1.1.dist-info/RECORD
