Metadata-Version: 2.1
Name: xThermal
Version: 0.1.1
Summary: Python API of xThermal package which is designed to calculate EOS and thermal dynamic properties of H2O, H2O-NaCl, and some other species in the near future.
Home-page: https://www.xthermo.cn
Author: Zhikui Guo
Author-email: zguo@geomar.de
Maintainer: Zhikui Guo
Maintainer-email: zguo@geomar.de
Keywords: NaCl H2O IAPWS Hydrothermal seawater
Classifier: Intended Audience :: Science/Research
Classifier: Intended Audience :: Developers
Classifier: Intended Audience :: Education
Classifier: Topic :: Scientific/Engineering
Classifier: Topic :: Software Development :: Libraries
Classifier: Programming Language :: Python :: 3.5
Classifier: Programming Language :: Python :: 3.6
Classifier: Programming Language :: Python :: 3.7
Classifier: Programming Language :: Python :: 3.8
Classifier: Programming Language :: Python :: 3.9
Requires-Dist: matplotlib >=3.5
Requires-Dist: numpy
Requires-Dist: argparse
